{
  "@context" : "http://iiif.io/api/presentation/2/context.json",
  "@id" : "https://noahjb27.github.io/img-jerusalem/manifests/historical-buildings-photography-manifest.json",
  "@type" : "sc:Manifest",
  "label" : "Historical Buildings Photographs",
  "metadata" : [ {
    "label" : "Title",
    "value" : "Jerusalem, 2023"
  }, {
    "label" : "Location",
    "value" : "Jerusalem"
  }, {
    "label" : "Photographer",
    "value" : "Noah Jefferson"
  }, {
    "label" : "Date",
    "value" : "1.03.2023"
  }, {
    "label" : "Description",
    "value" : "Photos taken during a visit to Jerusalem in early spring 2023."
  } ],
  "sequences" : [ {
    "@type" : "sc:Sequence",
    "label" : "Default Sequence",
    "canvases" : [ {
      "@type" : "sc:Canvas",
      "label" : "Armenian Church",
      "height" : 3024,
      "width" : 4032,
      "images" : [ {
        "@type" : "oa:Annotation",
        "motivation" : "oa:description",
        "resource" : {
          "@type" : "cnt:ContentAsText",
          "format" : "text/plain",
          "chars" : "This is the description for the Armenian Church."
        }
      } ]
    }, {
      "@type" : "sc:Canvas",
      "label" : "Dome of the Rock",
      "height" : 3024,
      "width" : 4032,
      "images" : [ {
        "@type" : "oa:Annotation",
        "motivation" : "oa:description",
        "resource" : {
          "@type" : "cnt:ContentAsText",
          "format" : "text/plain",
          "chars" : "This is the description for the Dome of the Rock."
        }
      } ]
    }, {
      "@type" : "sc:Canvas",
      "label" : "Suq Aftimos",
      "height" : 3024,
      "width" : 4032,
      "images" : [ {
        "@type" : "oa:Annotation",
        "motivation" : "oa:description",
        "resource" : {
          "@type" : "cnt:ContentAsText",
          "format" : "text/plain",
          "chars" : "This is the description for the Suq Aftimos."
        }
      } ]
    } ]
  } ]
}